server.py
mixpeek_mcp-0.1.0.dist-info/licenses/LICENSE
mixpeek_mcp-0.1.0.dist-info/METADATA
mixpeek_mcp-0.1.0.dist-info/WHEEL
mixpeek_mcp-0.1.0.dist-info/entry_points.txt
mixpeek_mcp-0.1.0.dist-info/top_level.txt
mixpeek_mcp-0.1.0.dist-info/RECORD
