Metadata-Version: 2.4
Name: mixpeek-mcp
Version: 0.1.0
Summary: Mixpeek MCP server (Python, stdio) auto-mapped from OpenAPI
Author: Mixpeek
License: MIT
Keywords: mcp,model-context-protocol,mixpeek,retrieval,openapi
Classifier: Programming Language :: Python :: 3
Classifier: License :: OSI Approved :: MIT License
Classifier: Operating System :: OS Independent
Requires-Python: >=3.9
License-File: LICENSE
Requires-Dist: httpx>=0.27.0
Requires-Dist: pydantic>=2.7.0
Requires-Dist: python-dotenv>=1.0.1
Provides-Extra: dev
Requires-Dist: pytest>=8; extra == "dev"
Requires-Dist: pytest-asyncio>=0.24; extra == "dev"
Dynamic: license-file
